teeraphancha/DHT11.py
teeraphancha/DHT22.py
teeraphancha/LINE.py
teeraphancha/__init__.py
teeraphancha/pi.py
teeraphancha/stock.py
teeraphancha/yolov3.py
teeraphancha-0.0.5.dist-info/LICENSE.txt
teeraphancha-0.0.5.dist-info/METADATA
teeraphancha-0.0.5.dist-info/WHEEL
teeraphancha-0.0.5.dist-info/top_level.txt
teeraphancha-0.0.5.dist-info/RECORD
