Metadata-Version: 2.1
Name: teeraphancha
Version: 0.0.5
Summary: Teeraphan Chanthongpugdee
Home-page: UNKNOWN
Author: Teeraphan Chanthongpugdee
Author-email: teeraphancha@hotmail.com
License: Teeraphancha
Keywords: teeraphancha,teeraphancha,teeraphancha,teeraphancha
Platform: UNKNOWN
Classifier: Development Status :: 3 - Alpha
Classifier: Intended Audience :: Developers
Classifier: Topic :: Software Development :: Build Tools
Classifier: License :: OSI Approved :: MIT License
Classifier: Programming Language :: Python :: 3
Classifier: Programming Language :: Python :: 3.4
Classifier: Programming Language :: Python :: 3.5
Classifier: Programming Language :: Python :: 3.6
Classifier: Programming Language :: Python :: 3.7
Classifier: Programming Language :: Python :: 3.8
Requires-Dist: teeraphancha
